dj_dashboard/__init__.py
dj_dashboard/constants.py
dj_dashboard/forms.py
dj_dashboard/models.py
dj_dashboard/urls.py
dj_dashboard/views.py
dj_dashboard/migrations/0001_initial.py
dj_dashboard/migrations/0002_dashboard_enable_edit.py
dj_dashboard/migrations/__init__.py
dj_dashboard/static/dj_dashboard/css/dj_dashboard.css
dj_dashboard/static/dj_dashboard/css/gridstack.min.css
dj_dashboard/static/dj_dashboard/css/semantic.min.localfont.css
dj_dashboard/static/dj_dashboard/css/components/accordion.css
dj_dashboard/static/dj_dashboard/css/components/accordion.js
dj_dashboard/static/dj_dashboard/css/components/accordion.min.css
dj_dashboard/static/dj_dashboard/css/components/accordion.min.js
dj_dashboard/static/dj_dashboard/css/components/ad.css
dj_dashboard/static/dj_dashboard/css/components/ad.min.css
dj_dashboard/static/dj_dashboard/css/components/api.js
dj_dashboard/static/dj_dashboard/css/components/api.min.js
dj_dashboard/static/dj_dashboard/css/components/breadcrumb.css
dj_dashboard/static/dj_dashboard/css/components/breadcrumb.min.css
dj_dashboard/static/dj_dashboard/css/components/button.css
dj_dashboard/static/dj_dashboard/css/components/button.min.css
dj_dashboard/static/dj_dashboard/css/components/card.css
dj_dashboard/static/dj_dashboard/css/components/card.min.css
dj_dashboard/static/dj_dashboard/css/components/checkbox.css
dj_dashboard/static/dj_dashboard/css/components/checkbox.js
dj_dashboard/static/dj_dashboard/css/components/checkbox.min.css
dj_dashboard/static/dj_dashboard/css/components/checkbox.min.js
dj_dashboard/static/dj_dashboard/css/components/colorize.js
dj_dashboard/static/dj_dashboard/css/components/colorize.min.js
dj_dashboard/static/dj_dashboard/css/components/comment.css
dj_dashboard/static/dj_dashboard/css/components/comment.min.css
dj_dashboard/static/dj_dashboard/css/components/container.css
dj_dashboard/static/dj_dashboard/css/components/container.min.css
dj_dashboard/static/dj_dashboard/css/components/dimmer.css
dj_dashboard-1.1.2.dist-info/AUTHORS.rst
dj_dashboard-1.1.2.dist-info/LICENSE
dj_dashboard-1.1.2.dist-info/METADATA
dj_dashboard-1.1.2.dist-info/WHEEL
dj_dashboard-1.1.2.dist-info/top_level.txt
dj_dashboard-1.1.2.dist-info/RECORD
