Metadata-Version: 2.1
Name: dj-dashboard
Version: 1.1.2
Summary: Django Dashboard
Home-page: https://gitlab.com/systent/dj_dashboard
Author: Claudio Mike Hofer
Author-email: claudio.h@systent.it
License: BSD
Keywords: dj_dashboard
Platform: UNKNOWN
Classifier: Development Status :: 5 - Production/Stable
Classifier: Framework :: Django
Classifier: Framework :: Django :: 1.8
Classifier: Framework :: Django :: 1.9
Classifier: Framework :: Django :: 1.10
Classifier: Intended Audience :: Developers
Classifier: License :: OSI Approved :: BSD License
Classifier: Natural Language :: English
Classifier: Programming Language :: Python :: 3
Classifier: Programming Language :: Python :: 3.2
Classifier: Programming Language :: Python :: 3.3
Classifier: Programming Language :: Python :: 3.4
Classifier: Programming Language :: Python :: 3.5
Requires-Dist: django-model-utils (>=2.0)
